[
    {
        "OBJECTID": "1",
        "PricePerArea": "14000",
        "F01_StrategicRoute": "520.015363411823",
        "F02_StreetRoad": "6.90316510005853",
        "F03_MTRstation": "215.418135048272",
        "F04_FutureMTRstation": "2731.53747623786",
        "F05_BusStop": "99.7744737855959",
        "F06_GMB": "154.640290702536",
        "F07_Hospital": "881.201656881776",
        "F08_SecondarySchool": "462.915457761997",
        "F10_Coastline": "3595.26165214473",
        "F11_Industry": "315.281979369736",
        "F14_OpenSpaceRecreation": "13.8859547966466",
        "F15_FutureDevelopmentNode": "592.540824213552",
        "Area": "236.255345990307",
        "S01_StrategicRoute": "5",
        "S02_StreetRoad": "0",
        "S03_MTRstation": "0",
        "S04_FutureMTRstation": "3",
        "S05_BusStop": "1",
        "S06_GMB": "0",
        "S07_Hospital": "0",
        "S08_SecondarySchool": "0",
        "EC01_Coastline": "4",
        "EC02_Industry": "3",
        "EC03_FutureDevelopmentNode": "0",
        "EN01_Coastline": "1",
        "EN04_OpenSpaceRecreation": "0",
        "EN05_Industry": "2",
        "EN02_StrategicRoute": "0",
        "EN03_StreetRoad": "5",
        "P01_LandUse": "3",
        "P02_Area": ""
    },
    {
        "OBJECTID": "2",
        "PricePerArea": "7183",
        "F01_StrategicRoute": "282.717418398767",
        "F02_StreetRoad": "144.964835975192",
        "F03_MTRstation": "2913.30855876643",
        "F04_FutureMTRstation": "681.19474171578",
        "F05_BusStop": "270.794253719424",
        "F06_GMB": "443.418055249052",
        "F07_Hospital": "3028.36934041499",
        "F08_SecondarySchool": "1445.13433045294",
        "F10_Coastline": "2948.46889987702",
        "F11_Industry": "0",
        "F14_OpenSpaceRecreation": "105.833382414251",
        "F15_FutureDevelopmentNode": "0",
        "Area": "20734.3712511738",
        "S01_StrategicRoute": "4",
        "S02_StreetRoad": "5",
        "S03_MTRstation": "3",
        "S04_FutureMTRstation": "0",
        "S05_BusStop": "5",
        "S06_GMB": "1",
        "S07_Hospital": "3",
        "S08_SecondarySchool": "3",
        "EC01_Coastline": "3",
        "EC02_Industry": "0",
        "EC03_FutureDevelopmentNode": "0",
        "EN01_Coastline": "2",
        "EN04_OpenSpaceRecreation": "0",
        "EN05_Industry": "5",
        "EN02_StrategicRoute": "1",
        "EN03_StreetRoad": "0",
        "P01_LandUse": "3",
        "P02_Area": ""
    },
    {
        "OBJECTID": "3",
        "PricePerArea": "8499",
        "F01_StrategicRoute": "279.376663853853",
        "F02_StreetRoad": "232.787483262214",
        "F03_MTRstation": "3020.25872113479",
        "F04_FutureMTRstation": "842.084717929416",
        "F05_BusStop": "266.89945549959",
        "F06_GMB": "483.497252164932",
        "F07_Hospital": "3207.02006463347",
        "F08_SecondarySchool": "1624.14725689103",
        "F10_Coastline": "2865.92959269096",
        "F11_Industry": "0",
        "F14_OpenSpaceRecreation": "245.196724776172",
        "F15_FutureDevelopmentNode": "0",
        "Area": "8801.68194865457",
        "S01_StrategicRoute": "4",
        "S02_StreetRoad": "5",
        "S03_MTRstation": "4",
        "S04_FutureMTRstation": "0",
        "S05_BusStop": "5",
        "S06_GMB": "1",
        "S07_Hospital": "3",
        "S08_SecondarySchool": "3",
        "EC01_Coastline": "3",
        "EC02_Industry": "0",
        "EC03_FutureDevelopmentNode": "0",
        "EN01_Coastline": "2",
        "EN04_OpenSpaceRecreation": "3",
        "EN05_Industry": "5",
        "EN02_StrategicRoute": "1",
        "EN03_StreetRoad": "0",
        "P01_LandUse": "1",
        "P02_Area": ""
    },
    {
        "OBJECTID": "4",
        "PricePerArea": "2690",
        "F01_StrategicRoute": "82.0174661435014",
        "F02_StreetRoad": "9.09924585024327",
        "F03_MTRstation": "1670.15613996665",
        "F04_FutureMTRstation": "503.474465202096",
        "F05_BusStop": "79.3612878464814",
        "F06_GMB": "562.070188454407",
        "F07_Hospital": "970.95348687675",
        "F08_SecondarySchool": "628.156879568329",
        "F10_Coastline": "4382.06530149683",
        "F11_Industry": "147.580059236938",
        "F14_OpenSpaceRecreation": "770.105766454315",
        "F15_FutureDevelopmentNode": "4670.70330155041",
        "Area": "33471.9962403677",
        "S01_StrategicRoute": "0",
        "S02_StreetRoad": "0",
        "S03_MTRstation": "2",
        "S04_FutureMTRstation": "0",
        "S05_BusStop": "0",
        "S06_GMB": "2",
        "S07_Hospital": "0",
        "S08_SecondarySchool": "0",
        "EC01_Coastline": "5",
        "EC02_Industry": "0",
        "EC03_FutureDevelopmentNode": "0",
        "EN01_Coastline": "0",
        "EN04_OpenSpaceRecreation": "5",
        "EN05_Industry": "5",
        "EN02_StrategicRoute": "5",
        "EN03_StreetRoad": "5",
        "P01_LandUse": "3",
        "P02_Area": ""
    },
    {
        "OBJECTID": "5",
        "PricePerArea": "9112",
        "F01_StrategicRoute": "1204.57018571214",
        "F02_StreetRoad": "3.73055500494194",
        "F03_MTRstation": "817.807257536584",
        "F04_FutureMTRstation": "2568.17660633543",
        "F05_BusStop": "97.3191646354138",
        "F06_GMB": "94.134277950721",
        "F07_Hospital": "1442.0165045118",
        "F08_SecondarySchool": "411.345462232819",
        "F10_Coastline": "2772.82192582482",
        "F11_Industry": "96.0672468043588",
        "F14_OpenSpaceRecreation": "47.2860358537546",
        "F15_FutureDevelopmentNode": "5083.38206897811",
        "Area": "17890.7048331889",
        "S01_StrategicRoute": "5",
        "S02_StreetRoad": "0",
        "S03_MTRstation": "0",
        "S04_FutureMTRstation": "3",
        "S05_BusStop": "1",
        "S06_GMB": "0",
        "S07_Hospital": "0",
        "S08_SecondarySchool": "0",
        "EC01_Coastline": "3",
        "EC02_Industry": "0",
        "EC03_FutureDevelopmentNode": "0",
        "EN01_Coastline": "2",
        "EN04_OpenSpaceRecreation": "0",
        "EN05_Industry": "5",
        "EN02_StrategicRoute": "0",
        "EN03_StreetRoad": "5",
        "P01_LandUse": "1",
        "P02_Area": ""
    },
    {
        "OBJECTID": "6",
        "PricePerArea": "8188",
        "F01_StrategicRoute": "126.826040281837",
        "F02_StreetRoad": "84.0786499700917",
        "F03_MTRstation": "997.070050256813",
        "F04_FutureMTRstation": "1336.50237132944",
        "F05_BusStop": "434.035967434594",
        "F06_GMB": "549.984361857986",
        "F07_Hospital": "1458.51125546464",
        "F08_SecondarySchool": "429.117824933917",
        "F10_Coastline": "4333.69928127667",
        "F11_Industry": "168.410400289888",
        "F14_OpenSpaceRecreation": "239.012382548552",
        "F15_FutureDevelopmentNode": "11891.4861174619",
        "Area": "2055.21324412112",
        "S01_StrategicRoute": "0",
        "S02_StreetRoad": "5",
        "S03_MTRstation": "0",
        "S04_FutureMTRstation": "0",
        "S05_BusStop": "5",
        "S06_GMB": "1",
        "S07_Hospital": "0",
        "S08_SecondarySchool": "0",
        "EC01_Coastline": "5",
        "EC02_Industry": "0",
        "EC03_FutureDevelopmentNode": "3",
        "EN01_Coastline": "0",
        "EN04_OpenSpaceRecreation": "3",
        "EN05_Industry": "5",
        "EN02_StrategicRoute": "5",
        "EN03_StreetRoad": "0",
        "P01_LandUse": "1",
        "P02_Area": ""
    },
    {
        "OBJECTID": "7",
        "PricePerArea": "9209",
        "F01_StrategicRoute": "145.253688629203",
        "F02_StreetRoad": "8.69164085782112",
        "F03_MTRstation": "598.244155133746",
        "F04_FutureMTRstation": "2307.51004655979",
        "F05_BusStop": "13.2819941667059",
        "F06_GMB": "349.730654746717",
        "F07_Hospital": "288.208583332544",
        "F08_SecondarySchool": "674.380270569992",
        "F10_Coastline": "3778.89128973194",
        "F11_Industry": "174.521158049504",
        "F14_OpenSpaceRecreation": "0",
        "F15_FutureDevelopmentNode": "805.887297581652",
        "Area": "5179.55016617516",
        "S01_StrategicRoute": "0",
        "S02_StreetRoad": "0",
        "S03_MTRstation": "0",
        "S04_FutureMTRstation": "3",
        "S05_BusStop": "0",
        "S06_GMB": "0",
        "S07_Hospital": "0",
        "S08_SecondarySchool": "0",
        "EC01_Coastline": "4",
        "EC02_Industry": "1",
        "EC03_FutureDevelopmentNode": "0",
        "EN01_Coastline": "1",
        "EN04_OpenSpaceRecreation": "0",
        "EN05_Industry": "4",
        "EN02_StrategicRoute": "5",
        "EN03_StreetRoad": "5",
        "P01_LandUse": "1",
        "P02_Area": ""
    },
    {
        "OBJECTID": "8",
        "PricePerArea": "4151",
        "F01_StrategicRoute": "241.896183494075",
        "F02_StreetRoad": "144.566324345025",
        "F03_MTRstation": "1163.32536439007",
        "F04_FutureMTRstation": "2941.02713654013",
        "F05_BusStop": "208.201717421087",
        "F06_GMB": "428.98743529992",
        "F07_Hospital": "1463.75933936255",
        "F08_SecondarySchool": "586.835500087712",
        "F10_Coastline": "4976.11026576657",
        "F11_Industry": "48.0222852614151",
        "F14_OpenSpaceRecreation": "284.569524853032",
        "F15_FutureDevelopmentNode": "6796.23416008549",
        "Area": "1316.03869367495",
        "S01_StrategicRoute": "3",
        "S02_StreetRoad": "5",
        "S03_MTRstation": "0",
        "S04_FutureMTRstation": "3",
        "S05_BusStop": "4",
        "S06_GMB": "0",
        "S07_Hospital": "0",
        "S08_SecondarySchool": "0",
        "EC01_Coastline": "5",
        "EC02_Industry": "0",
        "EC03_FutureDevelopmentNode": "1",
        "EN01_Coastline": "0",
        "EN04_OpenSpaceRecreation": "3",
        "EN05_Industry": "5",
        "EN02_StrategicRoute": "2",
        "EN03_StreetRoad": "0",
        "P01_LandUse": "3",
        "P02_Area": ""
    },
    {
        "OBJECTID": "9",
        "PricePerArea": "3500",
        "F01_StrategicRoute": "199.858660125175",
        "F02_StreetRoad": "7.21512681574446",
        "F03_MTRstation": "2036.64314295678",
        "F04_FutureMTRstation": "1377.23721310091",
        "F05_BusStop": "45.4637188931523",
        "F06_GMB": "142.17444067199",
        "F07_Hospital": "3318.20095632826",
        "F08_SecondarySchool": "570.407667657439",
        "F10_Coastline": "78.9693176399584",
        "F11_Industry": "365.92074259395",
        "F14_OpenSpaceRecreation": "27.6123160707192",
        "F15_FutureDevelopmentNode": "15662.8608150926",
        "Area": "6248.26936670676",
        "S01_StrategicRoute": "2",
        "S02_StreetRoad": "0",
        "S03_MTRstation": "2",
        "S04_FutureMTRstation": "0",
        "S05_BusStop": "0",
        "S06_GMB": "0",
        "S07_Hospital": "3",
        "S08_SecondarySchool": "0",
        "EC01_Coastline": "0",
        "EC02_Industry": "3",
        "EC03_FutureDevelopmentNode": "5",
        "EN01_Coastline": "5",
        "EN04_OpenSpaceRecreation": "0",
        "EN05_Industry": "2",
        "EN02_StrategicRoute": "3",
        "EN03_StreetRoad": "5",
        "P01_LandUse": "3",
        "P02_Area": ""
    },
    {
        "OBJECTID": "10",
        "PricePerArea": "6077",
        "F01_StrategicRoute": "32.0586205289175",
        "F02_StreetRoad": "15.8581422269278",
        "F03_MTRstation": "2984.83895115617",
        "F04_FutureMTRstation": "2379.09485020969",
        "F05_BusStop": "38.9257527041516",
        "F06_GMB": "877.952947830269",
        "F07_Hospital": "4116.39955728831",
        "F08_SecondarySchool": "1568.13116280543",
        "F10_Coastline": "177.861826883115",
        "F11_Industry": "841.471125099268",
        "F14_OpenSpaceRecreation": "19.8659249790382",
        "F15_FutureDevelopmentNode": "15549.7736575825",
        "Area": "15907.6048507184",
        "S01_StrategicRoute": "0",
        "S02_StreetRoad": "0",
        "S03_MTRstation": "4",
        "S04_FutureMTRstation": "3",
        "S05_BusStop": "0",
        "S06_GMB": "3",
        "S07_Hospital": "4",
        "S08_SecondarySchool": "3",
        "EC01_Coastline": "0",
        "EC02_Industry": "5",
        "EC03_FutureDevelopmentNode": "5",
        "EN01_Coastline": "5",
        "EN04_OpenSpaceRecreation": "0",
        "EN05_Industry": "0",
        "EN02_StrategicRoute": "5",
        "EN03_StreetRoad": "5",
        "P01_LandUse": "3",
        "P02_Area": ""
    },
    {
        "OBJECTID": "11",
        "PricePerArea": "6700",
        "F01_StrategicRoute": "204.267099492772",
        "F02_StreetRoad": "8.69092215470751",
        "F03_MTRstation": "3978.74870225867",
        "F04_FutureMTRstation": "3633.40131771282",
        "F05_BusStop": "6.14017367338468",
        "F06_GMB": "2061.05558098043",
        "F07_Hospital": "4853.5742928103",
        "F08_SecondarySchool": "2717.27127733515",
        "F10_Coastline": "694.143726918928",
        "F11_Industry": "196.645091009762",
        "F14_OpenSpaceRecreation": "459.910187128738",
        "F15_FutureDevelopmentNode": "14947.6856366958",
        "Area": "14341.1214323286",
        "S01_StrategicRoute": "2",
        "S02_StreetRoad": "0",
        "S03_MTRstation": "5",
        "S04_FutureMTRstation": "4",
        "S05_BusStop": "0",
        "S06_GMB": "5",
        "S07_Hospital": "5",
        "S08_SecondarySchool": "5",
        "EC01_Coastline": "0",
        "EC02_Industry": "1",
        "EC03_FutureDevelopmentNode": "5",
        "EN01_Coastline": "5",
        "EN04_OpenSpaceRecreation": "5",
        "EN05_Industry": "4",
        "EN02_StrategicRoute": "3",
        "EN03_StreetRoad": "5",
        "P01_LandUse": "3",
        "P02_Area": ""
    },
    {
        "OBJECTID": "12",
        "PricePerArea": "3343",
        "F01_StrategicRoute": "28.551279993553",
        "F02_StreetRoad": "13.2047749564425",
        "F03_MTRstation": "4500.44285663969",
        "F04_FutureMTRstation": "3971.51941178516",
        "F05_BusStop": "33.5356275137695",
        "F06_GMB": "2471.68566723436",
        "F07_Hospital": "5451.14252774105",
        "F08_SecondarySchool": "3157.17511358407",
        "F10_Coastline": "477.864103146375",
        "F11_Industry": "128.34214389038",
        "F14_OpenSpaceRecreation": "417.287817482179",
        "F15_FutureDevelopmentNode": "15654.1836669712",
        "Area": "8903.08356023319",
        "S01_StrategicRoute": "0",
        "S02_StreetRoad": "0",
        "S03_MTRstation": "5",
        "S04_FutureMTRstation": "5",
        "S05_BusStop": "0",
        "S06_GMB": "5",
        "S07_Hospital": "5",
        "S08_SecondarySchool": "5",
        "EC01_Coastline": "0",
        "EC02_Industry": "0",
        "EC03_FutureDevelopmentNode": "5",
        "EN01_Coastline": "5",
        "EN04_OpenSpaceRecreation": "5",
        "EN05_Industry": "5",
        "EN02_StrategicRoute": "5",
        "EN03_StreetRoad": "5",
        "P01_LandUse": "1",
        "P02_Area": ""
    },
    {
        "OBJECTID": "13",
        "PricePerArea": "4085",
        "F01_StrategicRoute": "52.7035279740484",
        "F02_StreetRoad": "2.30892757716967",
        "F03_MTRstation": "3155.7627989642",
        "F04_FutureMTRstation": "2621.03553929267",
        "F05_BusStop": "11.8720522784422",
        "F06_GMB": "1083.42167510771",
        "F07_Hospital": "4228.45057547715",
        "F08_SecondarySchool": "1772.44734001336",
        "F10_Coastline": "175.632611972997",
        "F11_Industry": "712.232628384424",
        "F14_OpenSpaceRecreation": "217.335712408071",
        "F15_FutureDevelopmentNode": "15480.1770208555",
        "Area": "18095.629677204",
        "S01_StrategicRoute": "0",
        "S02_StreetRoad": "0",
        "S03_MTRstation": "4",
        "S04_FutureMTRstation": "3",
        "S05_BusStop": "0",
        "S06_GMB": "4",
        "S07_Hospital": "4",
        "S08_SecondarySchool": "4",
        "EC01_Coastline": "0",
        "EC02_Industry": "5",
        "EC03_FutureDevelopmentNode": "5",
        "EN01_Coastline": "5",
        "EN04_OpenSpaceRecreation": "2",
        "EN05_Industry": "0",
        "EN02_StrategicRoute": "5",
        "EN03_StreetRoad": "5",
        "P01_LandUse": "1",
        "P02_Area": ""
    },
    {
        "OBJECTID": "14",
        "PricePerArea": "6499",
        "F01_StrategicRoute": "430.119986181299",
        "F02_StreetRoad": "6.17839100886174",
        "F03_MTRstation": "770.217920631206",
        "F04_FutureMTRstation": "2719.21807518304",
        "F05_BusStop": "401.1373530983",
        "F06_GMB": "0.28806779891778",
        "F07_Hospital": "666.680308278561",
        "F08_SecondarySchool": "611.807739308937",
        "F10_Coastline": "2938.80208598931",
        "F11_Industry": "629.528660919148",
        "F14_OpenSpaceRecreation": "268.008329847918",
        "F15_FutureDevelopmentNode": "13176.5032283425",
        "Area": "1243.54261188617",
        "S01_StrategicRoute": "5",
        "S02_StreetRoad": "0",
        "S03_MTRstation": "0",
        "S04_FutureMTRstation": "3",
        "S05_BusStop": "5",
        "S06_GMB": "0",
        "S07_Hospital": "0",
        "S08_SecondarySchool": "0",
        "EC01_Coastline": "3",
        "EC02_Industry": "5",
        "EC03_FutureDevelopmentNode": "4",
        "EN01_Coastline": "2",
        "EN04_OpenSpaceRecreation": "3",
        "EN05_Industry": "0",
        "EN02_StrategicRoute": "0",
        "EN03_StreetRoad": "5",
        "P01_LandUse": "1",
        "P02_Area": ""
    }
]